blackforest/__init__.py
blackforest/client.py
blackforest/resources/__init__.py
blackforest/resources/mapping/__init__.py
blackforest/resources/mapping/model_input_registry.py
blackforest/types/__init__.py
blackforest/types/base/__init__.py
blackforest/types/base/output_format.py
blackforest/types/general/__init__.py
blackforest/types/general/client_config.py
blackforest/types/inputs/__init__.py
blackforest/types/inputs/flux_dev.py
blackforest/types/inputs/flux_kontext_pro.py
blackforest/types/inputs/flux_pro.py
blackforest/types/inputs/flux_pro_1_1.py
blackforest/types/inputs/flux_pro_canny.py
blackforest/types/inputs/flux_pro_depth.py
blackforest/types/inputs/flux_pro_expand.py
blackforest/types/inputs/flux_pro_fill.py
blackforest/types/inputs/flux_ultra.py
blackforest/types/inputs/generic.py
blackforest/types/responses/__init__.py
blackforest/types/responses/responses.py
blackforest-0.1.3.dist-info/licenses/LICENSE
blackforest-0.1.3.dist-info/METADATA
blackforest-0.1.3.dist-info/WHEEL
blackforest-0.1.3.dist-info/top_level.txt
blackforest-0.1.3.dist-info/RECORD
