Metadata-Version: 2.4
Name: blackforest
Version: 0.1.3
Summary: The official Python library for the Black Forest Labs API
Author-email: Black Forest Labs <support@blackforestlabs.ai>
License: Apache-2.0
Project-URL: Homepage, https://github.com/black-forest-labs/blackforest
Project-URL: Source, https://github.com/black-forest-labs/blackforest
Project-URL: Documentation, https://blackforestlabs.ai/docs
Classifier: Development Status :: 3 - Alpha
Classifier: Intended Audience :: Developers
Classifier: License :: OSI Approved :: Apache Software License
Classifier: Programming Language :: Python :: 3
Classifier: Programming Language :: Python :: 3.7
Classifier: Programming Language :: Python :: 3.8
Classifier: Programming Language :: Python :: 3.9
Classifier: Programming Language :: Python :: 3.10
Classifier: Programming Language :: Python :: 3.11
Requires-Python: >=3.7
License-File: LICENSE
Requires-Dist: requests>=2.31.0
Requires-Dist: pydantic>=2.0.0
Requires-Dist: pillow==10.4.0
Dynamic: license-file
